pyfilecache/__init__.py
pyfilecache-0.1.6.dist-info/METADATA
pyfilecache-0.1.6.dist-info/WHEEL
pyfilecache-0.1.6.dist-info/top_level.txt
pyfilecache-0.1.6.dist-info/RECORD
