Metadata-Version: 2.1
Name: pyfilecache
Version: 0.1.6
Summary: cache the results of slow-running functions to disk, with multi-process safety
Home-page: https://github.com/HellOwhatAs/pyfilecache
Author: HellOwhatAs
Author-email: xjq701229@outlook.com
Classifier: Programming Language :: Python :: 3
Classifier: License :: OSI Approved :: MIT License
Classifier: Operating System :: OS Independent
Requires-Python: >=3.6
Requires-Dist: filelock
